{
	"backtrace" : 2,
	"backtraceGraph" : 
	{
		"commands" : 
		[
			"add_custom_target",
			"ei_add_test",
			"add_dependencies"
		],
		"files" : 
		[
			"cmake-build-debug/_deps/eigen-src/cmake/EigenTesting.cmake",
			"cmake-build-debug/_deps/eigen-src/test/CMakeLists.txt"
		],
		"nodes" : 
		[
			{
				"file" : 1
			},
			{
				"command" : 1,
				"file" : 1,
				"line" : 210,
				"parent" : 0
			},
			{
				"command" : 0,
				"file" : 0,
				"line" : 210,
				"parent" : 1
			},
			{
				"command" : 2,
				"file" : 0,
				"line" : 214,
				"parent" : 1
			},
			{
				"command" : 2,
				"file" : 0,
				"line" : 214,
				"parent" : 1
			},
			{
				"command" : 2,
				"file" : 0,
				"line" : 214,
				"parent" : 1
			},
			{
				"command" : 2,
				"file" : 0,
				"line" : 214,
				"parent" : 1
			},
			{
				"command" : 2,
				"file" : 0,
				"line" : 214,
				"parent" : 1
			},
			{
				"command" : 2,
				"file" : 0,
				"line" : 214,
				"parent" : 1
			},
			{
				"command" : 2,
				"file" : 0,
				"line" : 214,
				"parent" : 1
			},
			{
				"command" : 2,
				"file" : 0,
				"line" : 214,
				"parent" : 1
			},
			{
				"command" : 2,
				"file" : 0,
				"line" : 214,
				"parent" : 1
			},
			{
				"command" : 2,
				"file" : 0,
				"line" : 214,
				"parent" : 1
			},
			{
				"command" : 2,
				"file" : 0,
				"line" : 214,
				"parent" : 1
			},
			{
				"command" : 2,
				"file" : 0,
				"line" : 214,
				"parent" : 1
			},
			{
				"command" : 2,
				"file" : 0,
				"line" : 214,
				"parent" : 1
			},
			{
				"command" : 2,
				"file" : 0,
				"line" : 214,
				"parent" : 1
			},
			{
				"command" : 2,
				"file" : 0,
				"line" : 214,
				"parent" : 1
			},
			{
				"command" : 2,
				"file" : 0,
				"line" : 214,
				"parent" : 1
			},
			{
				"command" : 2,
				"file" : 0,
				"line" : 214,
				"parent" : 1
			},
			{
				"command" : 2,
				"file" : 0,
				"line" : 214,
				"parent" : 1
			},
			{
				"command" : 2,
				"file" : 0,
				"line" : 214,
				"parent" : 1
			},
			{
				"command" : 2,
				"file" : 0,
				"line" : 214,
				"parent" : 1
			},
			{
				"command" : 2,
				"file" : 0,
				"line" : 214,
				"parent" : 1
			},
			{
				"command" : 2,
				"file" : 0,
				"line" : 214,
				"parent" : 1
			},
			{
				"command" : 2,
				"file" : 0,
				"line" : 214,
				"parent" : 1
			},
			{
				"command" : 2,
				"file" : 0,
				"line" : 214,
				"parent" : 1
			},
			{
				"command" : 2,
				"file" : 0,
				"line" : 214,
				"parent" : 1
			}
		]
	},
	"dependencies" : 
	[
		{
			"backtrace" : 3,
			"id" : "product_trmm_1::@75e1563cc3333299b915"
		},
		{
			"backtrace" : 4,
			"id" : "product_trmm_11::@75e1563cc3333299b915"
		},
		{
			"backtrace" : 5,
			"id" : "product_trmm_111::@75e1563cc3333299b915"
		},
		{
			"backtrace" : 6,
			"id" : "product_trmm_21::@75e1563cc3333299b915"
		},
		{
			"backtrace" : 7,
			"id" : "product_trmm_121::@75e1563cc3333299b915"
		},
		{
			"backtrace" : 8,
			"id" : "product_trmm_31::@75e1563cc3333299b915"
		},
		{
			"backtrace" : 9,
			"id" : "product_trmm_131::@75e1563cc3333299b915"
		},
		{
			"backtrace" : 10,
			"id" : "product_trmm_12::@75e1563cc3333299b915"
		},
		{
			"backtrace" : 11,
			"id" : "product_trmm_112::@75e1563cc3333299b915"
		},
		{
			"backtrace" : 12,
			"id" : "product_trmm_22::@75e1563cc3333299b915"
		},
		{
			"backtrace" : 13,
			"id" : "product_trmm_122::@75e1563cc3333299b915"
		},
		{
			"backtrace" : 14,
			"id" : "product_trmm_32::@75e1563cc3333299b915"
		},
		{
			"backtrace" : 15,
			"id" : "product_trmm_132::@75e1563cc3333299b915"
		},
		{
			"backtrace" : 16,
			"id" : "product_trmm_13::@75e1563cc3333299b915"
		},
		{
			"backtrace" : 17,
			"id" : "product_trmm_113::@75e1563cc3333299b915"
		},
		{
			"backtrace" : 18,
			"id" : "product_trmm_23::@75e1563cc3333299b915"
		},
		{
			"backtrace" : 19,
			"id" : "product_trmm_123::@75e1563cc3333299b915"
		},
		{
			"backtrace" : 20,
			"id" : "product_trmm_33::@75e1563cc3333299b915"
		},
		{
			"backtrace" : 21,
			"id" : "product_trmm_133::@75e1563cc3333299b915"
		},
		{
			"backtrace" : 22,
			"id" : "product_trmm_14::@75e1563cc3333299b915"
		},
		{
			"backtrace" : 23,
			"id" : "product_trmm_114::@75e1563cc3333299b915"
		},
		{
			"backtrace" : 24,
			"id" : "product_trmm_24::@75e1563cc3333299b915"
		},
		{
			"backtrace" : 25,
			"id" : "product_trmm_124::@75e1563cc3333299b915"
		},
		{
			"backtrace" : 26,
			"id" : "product_trmm_34::@75e1563cc3333299b915"
		},
		{
			"backtrace" : 27,
			"id" : "product_trmm_134::@75e1563cc3333299b915"
		}
	],
	"id" : "product_trmm::@75e1563cc3333299b915",
	"name" : "product_trmm",
	"paths" : 
	{
		"build" : "_deps/eigen-build/test",
		"source" : "cmake-build-debug/_deps/eigen-src/test"
	},
	"sources" : [],
	"type" : "UTILITY"
}
